<?xml version="1.0" encoding="UTF-8" standalone="yes"?>
<w:document xmlns:wpc="http://schemas.microsoft.com/office/word/2010/wordprocessingCanvas" xmlns:mc="http://schemas.openxmlformats.org/markup-compatibility/2006" xmlns:o="urn:schemas-microsoft-com:office:office" xmlns:r="http://schemas.openxmlformats.org/officeDocument/2006/relationships" xmlns:m="http://schemas.openxmlformats.org/officeDocument/2006/math" xmlns:v="urn:schemas-microsoft-com:vml" xmlns:wp14="http://schemas.microsoft.com/office/word/2010/wordprocessingDrawing" xmlns:wp="http://schemas.openxmlformats.org/drawingml/2006/wordprocessingDrawing" xmlns:w10="urn:schemas-microsoft-com:office:word" xmlns:w="http://schemas.openxmlformats.org/wordprocessingml/2006/main" xmlns:w14="http://schemas.microsoft.com/office/word/2010/wordml" xmlns:wpg="http://schemas.microsoft.com/office/word/2010/wordprocessingGroup" xmlns:wpi="http://schemas.microsoft.com/office/word/2010/wordprocessingInk" xmlns:wne="http://schemas.microsoft.com/office/word/2006/wordml" xmlns:wps="http://schemas.microsoft.com/office/word/2010/wordprocessingShape" mc:Ignorable="w14 wp14"><w:body><w:p w:rsidR="00C66A9D" w:rsidRDefault="00CB7A5D"><w:r><w:rPr><w:rFonts w:ascii="Arial" w:hAnsi="Arial" w:cs="Arial"/><w:color w:val="333333"/><w:sz w:val="20"/><w:szCs w:val="20"/><w:shd w:val="clear" w:color="auto" w:fill="FFFFFF"/></w:rPr><w:t xml:space="preserve">Cross border investment professional with nearly two decades of experience in Silicon Valley and Asia’s venture capital industry. </w:t></w:r><w:proofErr w:type="gramStart"/><w:r><w:rPr><w:rFonts w:ascii="Arial" w:hAnsi="Arial" w:cs="Arial"/><w:color w:val="333333"/><w:sz w:val="20"/><w:szCs w:val="20"/><w:shd w:val="clear" w:color="auto" w:fill="FFFFFF"/></w:rPr><w:t>Extensive knowledge of venture lending, direct investment, venture fund investment, and corporate development, with emphasis on US and Asia cross-border transactions.</w:t></w:r><w:proofErr w:type="gramEnd"/><w:r><w:rPr><w:rFonts w:ascii="Arial" w:hAnsi="Arial" w:cs="Arial"/><w:color w:val="333333"/><w:sz w:val="20"/><w:szCs w:val="20"/><w:shd w:val="clear" w:color="auto" w:fill="FFFFFF"/></w:rPr><w:t xml:space="preserve"> Since 1995, Tony has been an active participant in Silicon Valley and Asia’s venture capital and entrepreneurial ecosystems, serving as an investment professional, angel investor, trusted advisor, and a catalyst to facilitate entrepreneurial value creation and capital formation. Completed over $200 million in venture debt financing to over 100 companies, invested in 25 privately-held technology startups, sponsored over 20 venture capital fund investments, and established an extensive network of relationships with venture capital firms, limited partners, entrepreneurs, corporate executives, and service providers on both sides of the Pacific.</w:t></w:r><w:r><w:rPr><w:rStyle w:val="apple-converted-space"/><w:rFonts w:ascii="Arial" w:hAnsi="Arial" w:cs="Arial"/><w:color w:val="333333"/><w:sz w:val="20"/><w:szCs w:val="20"/><w:shd w:val="clear" w:color="auto" w:fill="FFFFFF"/></w:rPr><w:t> </w:t></w:r><w:r><w:rPr><w:rFonts w:ascii="Arial" w:hAnsi="Arial" w:cs="Arial"/><w:color w:val="333333"/><w:sz w:val="20"/><w:szCs w:val="20"/></w:rPr><w:br/></w:r><w:r><w:rPr><w:rFonts w:ascii="Arial" w:hAnsi="Arial" w:cs="Arial"/><w:color w:val="333333"/><w:sz w:val="20"/><w:szCs w:val="20"/></w:rPr><w:br/></w:r><w:r><w:rPr><w:rFonts w:ascii="Arial" w:hAnsi="Arial" w:cs="Arial"/><w:color w:val="333333"/><w:sz w:val="20"/><w:szCs w:val="20"/><w:shd w:val="clear" w:color="auto" w:fill="FFFFFF"/></w:rPr><w:t xml:space="preserve">Tony has provided debt and equity financing to many market leading companies including Fortinet (FTNT), PayPal, Marvell (MRVL), </w:t></w:r><w:proofErr w:type="spellStart"/><w:r><w:rPr><w:rFonts w:ascii="Arial" w:hAnsi="Arial" w:cs="Arial"/><w:color w:val="333333"/><w:sz w:val="20"/><w:szCs w:val="20"/><w:shd w:val="clear" w:color="auto" w:fill="FFFFFF"/></w:rPr><w:t>PowerSet</w:t></w:r><w:proofErr w:type="spellEnd"/><w:r><w:rPr><w:rFonts w:ascii="Arial" w:hAnsi="Arial" w:cs="Arial"/><w:color w:val="333333"/><w:sz w:val="20"/><w:szCs w:val="20"/><w:shd w:val="clear" w:color="auto" w:fill="FFFFFF"/></w:rPr><w:t xml:space="preserve">, (acquired by Microsoft), Silicon Motion (SIMO), SMIC (SMI), </w:t></w:r><w:proofErr w:type="spellStart"/><w:r><w:rPr><w:rFonts w:ascii="Arial" w:hAnsi="Arial" w:cs="Arial"/><w:color w:val="333333"/><w:sz w:val="20"/><w:szCs w:val="20"/><w:shd w:val="clear" w:color="auto" w:fill="FFFFFF"/></w:rPr><w:t>TransMedia</w:t></w:r><w:proofErr w:type="spellEnd"/><w:r><w:rPr><w:rFonts w:ascii="Arial" w:hAnsi="Arial" w:cs="Arial"/><w:color w:val="333333"/><w:sz w:val="20"/><w:szCs w:val="20"/><w:shd w:val="clear" w:color="auto" w:fill="FFFFFF"/></w:rPr><w:t xml:space="preserve"> (acquired by Cisco), </w:t></w:r><w:proofErr w:type="spellStart"/><w:r><w:rPr><w:rFonts w:ascii="Arial" w:hAnsi="Arial" w:cs="Arial"/><w:color w:val="333333"/><w:sz w:val="20"/><w:szCs w:val="20"/><w:shd w:val="clear" w:color="auto" w:fill="FFFFFF"/></w:rPr><w:t>BCDsemi</w:t></w:r><w:proofErr w:type="spellEnd"/><w:r><w:rPr><w:rFonts w:ascii="Arial" w:hAnsi="Arial" w:cs="Arial"/><w:color w:val="333333"/><w:sz w:val="20"/><w:szCs w:val="20"/><w:shd w:val="clear" w:color="auto" w:fill="FFFFFF"/></w:rPr><w:t xml:space="preserve"> (BCDS), Carbonite (CARB), among others.</w:t></w:r><w:r><w:rPr><w:rFonts w:ascii="Arial" w:hAnsi="Arial" w:cs="Arial"/><w:color w:val="333333"/><w:sz w:val="20"/><w:szCs w:val="20"/></w:rPr><w:br/></w:r><w:r><w:rPr><w:rFonts w:ascii="Arial" w:hAnsi="Arial" w:cs="Arial"/><w:color w:val="333333"/><w:sz w:val="20"/><w:szCs w:val="20"/></w:rPr><w:br/></w:r><w:r><w:rPr><w:rFonts w:ascii="Arial" w:hAnsi="Arial" w:cs="Arial"/><w:color w:val="333333"/><w:sz w:val="20"/><w:szCs w:val="20"/><w:shd w:val="clear" w:color="auto" w:fill="FFFFFF"/></w:rPr><w:t>Specialties: Venture lending and equity investments.</w:t></w:r><w:bookmarkStart w:id="0" w:name="_GoBack"/><w:bookmarkEnd w:id="0"/></w:p><w:sectPr w:rsidR="00C66A9D"><w:pgSz w:w="12240" w:h="15840"/><w:pgMar w:top="1440" w:right="1440" w:bottom="1440" w:left="1440" w:header="720" w:footer="720" w:gutter="0"/><w:cols w:space="720"/><w:docGrid w:linePitch="360"/></w:sectPr></w:body></w:document>